zrag/__init__.py
zrag/chunk_node.py
zrag/data_generation.py
zrag/doc_loader.py
zrag/embeddings.py
zrag/llm.py
zrag/prompt_manager.py
zrag/rag_pipeline.py
zrag/vector_store.py
zrag-0.1.3.dist-info/LICENSE
zrag-0.1.3.dist-info/METADATA
zrag-0.1.3.dist-info/WHEEL
zrag-0.1.3.dist-info/top_level.txt
zrag-0.1.3.dist-info/RECORD
