Metadata-Version: 2.1
Name: zrag
Version: 0.1.3
Summary: A simple library for building Retrieval Augmented Generation (RAG) applications.
Author-email: Akshay Gautam <akshaygautam010@gmail.com>
Project-URL: Homepage, https://github.com/Ak-Gautam/sRAG 
Project-URL: Bug Tracker, https://github.com/Ak-Gautam/sRAG/issues
Classifier: Programming Language :: Python :: 3
Classifier: Operating System :: OS Independent
Classifier: Development Status :: 3 - Alpha
Classifier: Intended Audience :: Developers
Classifier: Topic :: Scientific/Engineering :: Artificial Intelligence
Classifier: Topic :: Software Development :: Libraries :: Python Modules
Requires-Python: >=3.9
License-File: LICENSE
Requires-Dist: torch
Requires-Dist: pymupdf
Requires-Dist: spacy
Requires-Dist: nltk
Requires-Dist: transformers
Requires-Dist: faiss-cpu
Requires-Dist: chromadb
Requires-Dist: jinja2
Requires-Dist: markdown
